blar_graph/__init__.py
blar_graph/agents_tools/agents_examples/debug.py
blar_graph/agents_tools/agents_examples/metamate.py
blar_graph/agents_tools/agents_examples/unit_test.py
blar_graph/agents_tools/tools/BaseCypherModel.py
blar_graph/agents_tools/tools/GetCodeByIdTool.py
blar_graph/agents_tools/tools/KeywordSearchTool.py
blar_graph/agents_tools/tools/__init__.py
blar_graph/db_managers/__init__.py
blar_graph/db_managers/base_manager.py
blar_graph/db_managers/json_manager.py
blar_graph/db_managers/neo4j_manager.py
blar_graph/graph_construction/core/graph_builder.py
blar_graph/graph_construction/languages/Parsers.py
blar_graph/graph_construction/languages/base_alias_extractor.py
blar_graph/graph_construction/languages/base_parser.py
blar_graph/graph_construction/languages/javascript/javascript_parser.py
blar_graph/graph_construction/languages/javascript/jsx_parser.py
blar_graph/graph_construction/languages/python/python_parser.py
blar_graph/graph_construction/languages/ruby/ruby_parser.py
blar_graph/graph_construction/languages/typescript/tsx_parser.py
blar_graph/graph_construction/languages/typescript/typescript_parser.py
blar_graph/graph_construction/utils/__init__.py
blar_graph/graph_construction/utils/format_nodes.py
blar_graph/graph_construction/utils/interfaces/GlobalGraphInfo.py
blar_graph/run.py
blar_graph-1.1.6.dist-info/LICENSE
blar_graph-1.1.6.dist-info/METADATA
blar_graph-1.1.6.dist-info/WHEEL
blar_graph-1.1.6.dist-info/RECORD
